CHANGELOG.txt
LICENCE.txt
MANIFEST.in
README.txt
setup.py
Carters_Calcuator/__init__.py
Carters_Calcuator.egg-info/PKG-INFO
Carters_Calcuator.egg-info/SOURCES.txt
Carters_Calcuator.egg-info/dependency_links.txt
Carters_Calcuator.egg-info/top_level.txt