Metadata-Version: 1.1
Name: Carters-Calcuator
Version: 0.0.1
Summary: A very basic calculator in the console
Home-page: UNKNOWN
Author: Carter Hagans
Author-email: carterhagans@gmail.com
License: MIT
Keywords: calculator
Platform: UNKNOWN
Classifier: Development Status :: 5 - Production/Stable
Classifier: Intended Audience :: Education
Classifier: Operating System :: Microsoft :: Windows :: Windows 10
Classifier: License :: OSI Approved :: MIT License
Classifier: Programming Language :: Python :: 3
